Metadata-Version: 1.0
Name: cracker-say
Version: 1.9
Summary: This PIP only made for designing Tool and Termux Bennar
Home-page: https://github.com/cracker911181/cracker_enc
Author: cracker911181
Author-email: UNKNOWN
License: UNKNOWN
Platform: UNKNOWN
